scripts/__init__.py
scripts/caltech_download.py
scripts/create_issues_report.py
scripts/dataverse_download.py
scripts/gitter_stats.py
scripts/make_qr_code.py
scripts/osf_download.py
scripts/upgrade_simba_keep_configs.py
simba/.DS_Store
simba/SimBA.py
simba/SimBA_logo.ico
simba/__init__.py
simba/requirements.txt
simba/assets/.DS_Store
simba/assets/.env
simba/assets/.recent_projects.txt
simba/assets/TheGoldenLab.PNG
simba/assets/UbuntuMono-Regular.ttf
simba/assets/__init__.py
simba/assets/botsort.yml
simba/assets/bytetrack.yml
simba/assets/dash_simba_base.css
simba/assets/tow_bytetrack.yaml
simba/assets/fonts/.DS_Store
simba/assets/fonts/Playwrite ES Deco.ttf
simba/assets/fonts/Poppins Bold.ttf
simba/assets/fonts/Poppins Regular.ttf
simba/assets/fonts/UbuntuMono-Regular.ttf
simba/assets/icons/.DS_Store
simba/assets/icons/SimBA_logo.icns
simba/assets/icons/SimBA_logo.ico
simba/assets/icons/SimBA_logo.png
simba/assets/icons/SimBA_logo_3.ico
simba/assets/icons/SimBA_logo_3.png
simba/assets/icons/SimBA_logo_3_small.png
simba/assets/icons/SimBA_logo_4_small.png
simba/assets/icons/__init__.py
simba/assets/icons/abacus.png
simba/assets/icons/abacus_2.png
simba/assets/icons/abacus_3.png
simba/assets/icons/about.png
simba/assets/icons/add.png
simba/assets/icons/add_on.png
simba/assets/icons/analyze_blue.png
simba/assets/icons/analyze_green.png
simba/assets/icons/api.png
simba/assets/icons/application.png
simba/assets/icons/archive.png
simba/assets/icons/arrow_down_green.png
simba/assets/icons/arrow_down_green_2.png
simba/assets/icons/attributes_large.png
simba/assets/icons/audio.png
simba/assets/icons/average.png
simba/assets/icons/average_2.png
simba/assets/icons/avi.png
simba/assets/icons/bar_graph_blue.png
simba/assets/icons/bar_graph_green.png
simba/assets/icons/bar_graph_light_blue.png
simba/assets/icons/batch.png
simba/assets/icons/black_and_white.png
simba/assets/icons/black_cross.png
simba/assets/icons/blur.png
simba/assets/icons/bmp.png
simba/assets/icons/bold.png
simba_uw_tf_dev-4.6.4.dist-info/LICENSE
simba_uw_tf_dev-4.6.4.dist-info/METADATA
simba_uw_tf_dev-4.6.4.dist-info/WHEEL
simba_uw_tf_dev-4.6.4.dist-info/entry_points.txt
simba_uw_tf_dev-4.6.4.dist-info/top_level.txt
simba_uw_tf_dev-4.6.4.dist-info/RECORD
